MANIFEST.in
README.rst
setup.cfg
setup.py
sphinxcontrib/__init__.py
sphinxcontrib/externallinks.py
sphinxcontrib_externallinks.egg-info/PKG-INFO
sphinxcontrib_externallinks.egg-info/SOURCES.txt
sphinxcontrib_externallinks.egg-info/dependency_links.txt
sphinxcontrib_externallinks.egg-info/namespace_packages.txt
sphinxcontrib_externallinks.egg-info/not-zip-safe
sphinxcontrib_externallinks.egg-info/requires.txt
sphinxcontrib_externallinks.egg-info/top_level.txt