Metadata-Version: 1.0
Name: sphinxcontrib-externallinks
Version: 0.1dev-20131017
Summary: Sphinx "externallinks" extension
Home-page: https://github.com/MiCHiLU/sphinxcontrib-externallinks
Author: ENDOH takanao
Author-email: UNKNOWN
License: BSD
Download-URL: http://pypi.python.org/pypi/sphinxcontrib-externallinks
Platform: any
Classifier: Development Status :: 4 - Beta
Classifier: Environment :: Console
Classifier: Environment :: Web Environment
Classifier: Intended Audience :: Developers
Classifier: License :: OSI Approved :: BSD License
Classifier: Operating System :: OS Independent
Classifier: Programming Language :: Python
Classifier: Topic :: Documentation
Classifier: Topic :: Utilities
